pytest_solidity/__init__.py
pytest_solidity-0.0.0.dev1.dist-info/LICENSE
pytest_solidity-0.0.0.dev1.dist-info/METADATA
pytest_solidity-0.0.0.dev1.dist-info/WHEEL
pytest_solidity-0.0.0.dev1.dist-info/top_level.txt
pytest_solidity-0.0.0.dev1.dist-info/RECORD
